{"\ud3f4\ub9c1\ubc29\uc2dd": "\ud3f4\ub9c1 \ubc29\uc2dd\uc740 \ubcf4\ud1b5 busy-waiting\uc758 \uacbd\uc6b0\ub85c \uacc4\uc18d \ub8e8\ud504\ub97c \ub3cc\uc544\uc11c CPU \uc2dc\uac04\uc744 \ub0ad\ube44\ud569\ub2c8\ub2e4. ", "\ud398\uc774\uc9d5": "\ud398\uc774\uc9c0 \ud14c\uc774\ube14\uc774 \ucd94\uac00\ub85c \ud544\uc694\ud558\ub2e4.", "\ub9c8\uc774\ud06c\ub85c\ucee4\ub110": "\ub2e8\uc810\uc73c\ub85c\ub294 \ud30c\uc77c\uc11c\ube44\uc2a4 \ub4f1\uc5d0 \uc788\uc5b4\uc11c \ud504\ub85c\uc138\uc2a4\uc758 \ubb38\ub9e5\uad50\ud658\uacfc \uba54\uc2dc\uc9c0 \uc804\uc1a1\uc774 \ube48\ubc88\ud574\uc838\uc11c \uc18d\ub3c4\uac00 \ub290\ub824\uc9c8 \uc218 \uc788\ub294 \ub4f1 \uc804\ubc18\uc801\uc73c\ub85c \uc131\ub2a5\uc774 \uc800\ud558 \ub420 \uc218 \uc788\ub2e4\ub294 \uc810\uc774 \ub2e8\uc810\uc73c\ub85c \uac70\ub860\ub420 \uc218 \uc788\uaca0\uc2b5\ub2c8\ub2e4.", "\ubaa8\ub178\ub9ac\ud2f1\ucee4\ub110": "\ub2e8\uc810\uc73c\ub85c\ub294 \uc0c8\ub85c\uc6b4 \ud558\ub4dc\uc6e8\uc5b4 \ud50c\ub7ab\ud3fc\uc5d0 \ub300\ud55c \uc774\uc2dd\uc131\uc774 \ub5a8\uc5b4\uc9c0\uace0, \ud55c \ubd80\ubd84\uc5d0\uc11c \ubc1c\uc0dd\ud55c \ubb38\uc81c\uac00 \uc2dc\uc2a4\ud15c \uc804\uccb4\uc5d0 \uc601\ud5a5\uc744 \uc904 \uc218 \uc788\ub2e4\ub294 \uc810\uacfc, \uad6c\uc131\uc694\uc18c\ub4e4 \uac04\uc758 \uc758\uc874\uc131\uc774 \ub192\uc544\uc838 \ub514\ubc84\uae45\uc774 \uc5b4\ub824\uc6cc\uc9c8 \uc218 \uc788\ub2e4\ub294 \uc810 \ub4f1\uc744 \ub4e4 \uc218 \uc788\uaca0\uc2b5\ub2c8\ub2e4.", "\ubd84\ud560\ubc29\ubc95": "\uc678\ubd80\ub2e8\ud3b8\ud654\uac00 \ubc1c\uc0dd\ud560 \uc218 \uc788\ub2e4\ub294 \ub2e8\uc810\uc774 \uc788\ub2e4.", "\uc9c1\uc811\uc785\ucd9c\ub825\ubc29\uc2dd": "\ub300\uc6a9\ub7c9\uc758 \uc785\ucd9c\ub825\uc744 \uc704\ud55c \uc7a5\uce58 (\uc608: \ud558\ub4dc\ub514\uc2a4\ud06c) \uc5d0 \uc0ac\uc6a9\ud558\uae30\uc5d0 \uc801\uc808\ud558\uc9c0 \uc54a\uc2b5\ub2c8\ub2e4. \ube14\ub85d\uc758 \ub2e8\uc704\uac00 \ubcf4\ud1b5 512\ubc14\uc774\ud2b8\ub77c\uace0 \ubcfc \ub54c \uace0\uc18d \uc785\ucd9c\ub825\uc744 \uc704\ud574\uc11c\ub294 \ube14\ub85d \ub2e8\uc704\ub85c \uc778\ud130\ub7fd\ud2b8\ub97c \ucc98\ub9ac\ud574\uc57c\uc9c0, \ud55c \ube14\ub85d\uc758 \uc785\ucd9c\ub825\uc744 \uc704\ud574 512\ubc88\uc758 \uc778\ud130\ub7fd\ud2b8\ub97c \ucc98\ub9ac\ud560 \uc218\ub294 \uc5c6\ub294 \ub178\ub987\uc774\uae30 \ub54c\ubb38\uc785\ub2c8\ub2e4."}